LICENSE
MANIFEST.in
README.rst
setup.py
fiduswriter/github_export/__init__.py
fiduswriter/github_export/admin.py
fiduswriter/github_export/apps.py
fiduswriter/github_export/models.py
fiduswriter/github_export/proxy_views.py
fiduswriter/github_export/urls.py
fiduswriter/github_export/views.py
fiduswriter/github_export/locale/bg/LC_MESSAGES/djangojs.mo
fiduswriter/github_export/locale/bg/LC_MESSAGES/djangojs.po
fiduswriter/github_export/locale/de/LC_MESSAGES/djangojs.mo
fiduswriter/github_export/locale/de/LC_MESSAGES/djangojs.po
fiduswriter/github_export/locale/es/LC_MESSAGES/djangojs.mo
fiduswriter/github_export/locale/es/LC_MESSAGES/djangojs.po
fiduswriter/github_export/locale/fr/LC_MESSAGES/djangojs.mo
fiduswriter/github_export/locale/fr/LC_MESSAGES/djangojs.po
fiduswriter/github_export/locale/it/LC_MESSAGES/djangojs.mo
fiduswriter/github_export/locale/it/LC_MESSAGES/djangojs.po
fiduswriter/github_export/locale/pt_BR/LC_MESSAGES/djangojs.mo
fiduswriter/github_export/locale/pt_BR/LC_MESSAGES/djangojs.po
fiduswriter/github_export/migrations/0001_initial.py
fiduswriter/github_export/migrations/0002_auto_20200411_2148.py
fiduswriter/github_export/migrations/0003_alter_bookrepository_options.py
fiduswriter/github_export/migrations/0004_bookrepository_export_unified_html.py
fiduswriter/github_export/migrations/0005_repoinfo.py
fiduswriter/github_export/migrations/__init__.py
fiduswriter/github_export/static/js/modules/github_export/book_exporters.js
fiduswriter/github_export/static/js/modules/github_export/book_processor.js
fiduswriter/github_export/static/js/modules/github_export/books_overview.js
fiduswriter/github_export/static/js/modules/github_export/index.js
fiduswriter/github_export/static/js/modules/github_export/templates.js
fiduswriter/github_export/static/js/modules/github_export/tools/basic.js
fiduswriter/github_export/static/js/modules/github_export/tools/commit_file.js
fiduswriter/github_export/static/js/modules/github_export/tools/commit_tree.js
fiduswriter_github_export.egg-info/PKG-INFO
fiduswriter_github_export.egg-info/SOURCES.txt
fiduswriter_github_export.egg-info/dependency_links.txt
fiduswriter_github_export.egg-info/top_level.txt