Metadata-Version: 1.1
Name: fiduswriter-github-export
Version: 3.10.5
Summary: A Fidus Writer plugin to allow publishing of books to Github
Home-page: https://www.github.org/fiduswriter/fiduswriter-github-export
Author: Johannes Wilm
Author-email: johannes@fiduswriter.org
License: AGPL License
Platform: UNKNOWN
Classifier: Environment :: Web Environment
Classifier: Framework :: Django
Classifier: Framework :: Django :: 3.2
Classifier: Intended Audience :: Developers
Classifier: License :: OSI Approved :: GNU Affero General Public License v3
Classifier: Operating System :: OS Independent
Classifier: Programming Language :: Python
Classifier: Programming Language :: Python :: 3
Classifier: Topic :: Internet :: WWW/HTTP
Classifier: Topic :: Internet :: WWW/HTTP :: Dynamic Content
